README.txt
setup.py
RE_1/RE_1.py
RE_1/__init__.py
RE_1/config.py
RE_1/stats.py
RE_1/zombie_combat.py
RE_1.egg-info/PKG-INFO
RE_1.egg-info/SOURCES.txt
RE_1.egg-info/dependency_links.txt
RE_1.egg-info/requires.txt
RE_1.egg-info/top_level.txt