Metadata-Version: 1.1
Name: RE-1
Version: 0.1
Summary: A Resident Evil Game
Home-page: http://pypi.python.org/pypi/RE_1
Author: Barbara Rodriguez
Author-email: barbarajrodriguez542@gmail.com
License: UNKNOWN
Download-URL: http://pypi.python.org/pypi/RE_1
Platform: UNKNOWN
